wharf/__init__.py
wharf/__main__.py
wharf/api.py
wharf/cli.py
wharf/configuration.py
wharf/context_globals.py
wharf/process_manager.py
wharf/properties.py
wharf/settings.py
wharf/docker/entrypoint
wharf/templates/systemd.j2
wharf-2.0.3.dist-info/METADATA
wharf-2.0.3.dist-info/WHEEL
wharf-2.0.3.dist-info/entry_points.txt
wharf-2.0.3.dist-info/top_level.txt
wharf-2.0.3.dist-info/RECORD
