Metadata-Version: 2.1
Name: wharf
Version: 2.0.3
Summary: A docker environment manager
Home-page: https://github.com/NazarethCollege/wharf
Author: Dave Lafferty
Author-email: web_tech@naz.edu
License: MIT
Keywords: docker development
Platform: UNKNOWN
Classifier: Development Status :: 3 - Alpha
Classifier: Intended Audience :: Developers
Classifier: Topic :: Software Development :: Build Tools
Classifier: License :: OSI Approved :: MIT License
Classifier: Programming Language :: Python :: 3
Requires-Dist: click (<8)
Requires-Dist: docker (==5.0.3)
Requires-Dist: dockerpty (<0.5)
Requires-Dist: jinja2 (>=3.0.0)
Requires-Dist: templated-yaml (>=1.1.3)
